sachitpkg/__init__.py
sachitpkg-0.1.0.dist-info/WHEEL
sachitpkg-0.1.0.dist-info/METADATA
sachitpkg-0.1.0.dist-info/RECORD
