Metadata-Version: 2.1
Name: sachitpkg
Version: 0.1.0
Summary: 
Author: Your Name
Author-email: you@example.com
Requires-Python: >=2.7,<3.0
Classifier: Programming Language :: Python :: 2
Classifier: Programming Language :: Python :: 2.7
Requires-Dist: pyspark (>=3.0.1,<4.0.0)
Requires-Dist: requests (>=2.24.0,<3.0.0)
